desc_dict_io/__init__.py
desc_dict_io/_version.py
desc_dict_io/errors.py
desc_dict_io/ioUtils.py
desc_dict_io/types.py
desc_dict_io/utils.py
desc_dict_io-0.2.dist-info/LICENSE
desc_dict_io-0.2.dist-info/METADATA
desc_dict_io-0.2.dist-info/WHEEL
desc_dict_io-0.2.dist-info/top_level.txt
desc_dict_io-0.2.dist-info/RECORD
