Metadata-Version: 2.1
Name: desc-dict-io
Version: 0.2
Summary: Dictionary IO to various file types
Author-email: Joe Zuntz <joe.zuntz@ed.ac.uk>, Eric Charles <echarles@slac.stanford.edu>
License: BSD 3-Clause License        
Classifier: Development Status :: 4 - Beta
Classifier: License :: OSI Approved :: BSD License
Classifier: Intended Audience :: Developers
Classifier: Intended Audience :: Science/Research
Classifier: Programming Language :: Python
Classifier: Programming Language :: Python :: 3
Classifier: Programming Language :: Python :: 3.8
Classifier: Programming Language :: Python :: 3.9
Classifier: Programming Language :: Python :: 3.10
Classifier: Natural Language :: English
Classifier: Operating System :: POSIX
Requires-Python: >=3.8
License-File: LICENSE
Requires-Dist: numpy
Provides-Extra: all
Requires-Dist: ruamel.yaml ; extra == 'all'
Requires-Dist: fitsio ; extra == 'all'
Requires-Dist: h5py ; extra == 'all'
Provides-Extra: dev
Requires-Dist: coverage ; extra == 'dev'
Requires-Dist: pylint ; extra == 'dev'
Requires-Dist: pytest ; extra == 'dev'
Requires-Dist: pytest-cov ; extra == 'dev'
Requires-Dist: flake8 ; extra == 'dev'
Requires-Dist: ruamel.yaml ; extra == 'dev'
Requires-Dist: fitsio ; extra == 'dev'
Requires-Dist: h5py ; extra == 'dev'
Provides-Extra: fits
Requires-Dist: fitsio ; extra == 'fits'
Provides-Extra: hdf
Requires-Dist: h5py ; extra == 'hdf'
Provides-Extra: yaml
Requires-Dist: ruamel.yaml ; extra == 'yaml'
